aleat3/__init__.py
aleat3/constructor.py
aleat3/applications/__init__.py
aleat3/applications/coinWinners.py
aleat3/applications/diceInterface.py
aleat3/applications/diceMove.py
aleat3/applications/rouletteWinners.py
aleat3/output/__init__.py
aleat3/output/colored.py
aleat3/output/init_errors.py
aleat3-0.2.9.dist-info/LICENSE
aleat3-0.2.9.dist-info/METADATA
aleat3-0.2.9.dist-info/WHEEL
aleat3-0.2.9.dist-info/top_level.txt
aleat3-0.2.9.dist-info/RECORD
