Metadata-Version: 2.1
Name: aleat3
Version: 0.2.9
Summary: An aleatory syntaxes package. Third generation.
Home-page: https://github.com/diddileija/aleat3/blob/main/README.md
Author: Diego Ramirez
Author-email: dr01191115@gmail.com
License: UNKNOWN
Keywords: aleatory dice coin roulette python aleat
Platform: UNKNOWN
Classifier: Development Status :: 5 - Production/Stable
Classifier: Intended Audience :: Customer Service
Classifier: Intended Audience :: Education
Classifier: Intended Audience :: Developers
Classifier: Natural Language :: English
Classifier: Programming Language :: Python :: 3
Classifier: Programming Language :: Python :: 3.6
Classifier: Programming Language :: Python :: 3.7
Classifier: Programming Language :: Python :: 3.8
Classifier: Programming Language :: Python :: 3.9
Classifier: License :: OSI Approved :: MIT License
Classifier: Operating System :: OS Independent
Classifier: Operating System :: MacOS
Classifier: Operating System :: MacOS :: MacOS X
Classifier: Operating System :: Microsoft
Classifier: Operating System :: Microsoft :: Windows
Classifier: Operating System :: Microsoft :: Windows :: Windows 7
Classifier: Operating System :: Microsoft :: Windows :: Windows 8
Classifier: Operating System :: Unix
Classifier: Topic :: Games/Entertainment
Classifier: Topic :: Software Development
Requires-Python: >=3.6, <3.10
